{
  "student": "Rajeshwari1459-frontend",
  "track": "frontend",
  "trackTitle": [
    "HTML & CSS",
    "HTML & CSS",
    "Computer & Git Basics",
    "HTML & CSS",
    "HTML & CSS",
    "React & Next.js",
    "HTML & CSS",
    "React & Next.js",
    "JavaScript Fundamentals",
    "React & Next.js",
    "React & Next.js",
    "JavaScript Fundamentals",
    "React & Next.js",
    "TypeScript",
    "HTML & CSS",
    "Computer & Git Basics",
    "TypeScript",
    "React & Next.js",
    "JavaScript Fundamentals",
    "JavaScript Fundamentals",
    "JavaScript Fundamentals",
    "TypeScript",
    "JavaScript Fundamentals",
    "JavaScript Fundamentals",
    "React & Next.js",
    "TypeScript",
    "Computer & Git Basics",
    "JavaScript Fundamentals",
    "JavaScript Fundamentals",
    "HTML & CSS",
    "JavaScript Fundamentals",
    "JavaScript Fundamentals",
    "JavaScript Fundamentals",
    "JavaScript Fundamentals",
    "TypeScript",
    "React & Next.js",
    "JavaScript Fundamentals",
    "JavaScript Fundamentals",
    "TypeScript",
    "JavaScript Fundamentals",
    "React & Next.js",
    "JavaScript Fundamentals",
    "React & Next.js",
    "Computer & Git Basics",
    "React & Next.js",
    "HTML & CSS",
    "JavaScript Fundamentals",
    "JavaScript Fundamentals",
    "React & Next.js",
    "TypeScript",
    "TypeScript",
    "JavaScript Fundamentals",
    "TypeScript",
    "HTML & CSS",
    "React & Next.js",
    "React & Next.js",
    "React & Next.js",
    "React & Next.js",
    "React & Next.js",
    "React & Next.js",
    "HTML & CSS",
    "HTML & CSS",
    "TypeScript",
    "Computer & Git Basics",
    "React & Next.js",
    "Computer & Git Basics",
    "JavaScript Fundamentals",
    "HTML & CSS",
    "Computer & Git Basics",
    "JavaScript Fundamentals",
    "JavaScript Fundamentals"
  ],
  "generatedAt": "2026-06-11T14:57:21.0856727Z",
  "verifiedBy": "techmonster-dev",
  "progressPct": 0,
  "status": "on-track",
  "projects": []
}